perplex/__init__.py
perplex/__main__.py
perplex/cli.py
perplex-0.0.1.dist-info/METADATA
perplex-0.0.1.dist-info/RECORD
perplex-0.0.1.dist-info/WHEEL
perplex-0.0.1.dist-info/entry_points.txt
perplex-0.0.1.dist-info/top_level.txt
